odoo10_addon_l10n_it_invoices_data_communication_fatturapa-10.0.1.0.0.99.dev4-py3.8-nspkg.pth
odoo/addons/l10n_it_invoices_data_communication_fatturapa/README.rst
odoo/addons/l10n_it_invoices_data_communication_fatturapa/__init__.py
odoo/addons/l10n_it_invoices_data_communication_fatturapa/__manifest__.py
odoo/addons/l10n_it_invoices_data_communication_fatturapa/i18n/l10n_it_invoices_data_communication_fatturapa.pot
odoo/addons/l10n_it_invoices_data_communication_fatturapa/models/__init__.py
odoo/addons/l10n_it_invoices_data_communication_fatturapa/models/communication.py
odoo/addons/l10n_it_invoices_data_communication_fatturapa/readme/CONTRIBUTORS.rst
odoo/addons/l10n_it_invoices_data_communication_fatturapa/readme/DESCRIPTION.rst
odoo/addons/l10n_it_invoices_data_communication_fatturapa/static/description/icon.png
odoo/addons/l10n_it_invoices_data_communication_fatturapa/static/description/index.html
odoo/addons/l10n_it_invoices_data_communication_fatturapa/views/communication_view.xml
odoo10_addon_l10n_it_invoices_data_communication_fatturapa-10.0.1.0.0.99.dev4.dist-info/METADATA
odoo10_addon_l10n_it_invoices_data_communication_fatturapa-10.0.1.0.0.99.dev4.dist-info/WHEEL
odoo10_addon_l10n_it_invoices_data_communication_fatturapa-10.0.1.0.0.99.dev4.dist-info/namespace_packages.txt
odoo10_addon_l10n_it_invoices_data_communication_fatturapa-10.0.1.0.0.99.dev4.dist-info/top_level.txt
odoo10_addon_l10n_it_invoices_data_communication_fatturapa-10.0.1.0.0.99.dev4.dist-info/RECORD
