Metadata-Version: 2.1
Name: odoo10-addon-l10n-it-invoices-data-communication-fatturapa
Version: 10.0.1.0.0.99.dev4
Summary: Integrazione fatturazione elettronica e Comunicazione dati fatture (c.d. "nuovo spesometro")
Home-page: https://github.com/OCA/l10n-italy/
Author: Agile Business Group, Odoo Community Association (OCA)
Author-email: support@odoo-community.org
License: LGPL-3
Platform: UNKNOWN
Classifier: Programming Language :: Python
Classifier: Framework :: Odoo
Classifier: Framework :: Odoo :: 10.0
Classifier: License :: OSI Approved :: GNU Lesser General Public License v3 (LGPLv3)
Requires-Python: ~=2.7
Requires-Dist: odoo10-addon-l10n-it-fatturapa-in
Requires-Dist: odoo10-addon-l10n-it-fatturapa-out
Requires-Dist: odoo10-addon-l10n-it-invoices-data-communication
Requires-Dist: odoo <10.1dev,>=10.0
